brownie_safe.py
brownie_safe-0.9.2.dist-info/METADATA
brownie_safe-0.9.2.dist-info/WHEEL
brownie_safe-0.9.2.dist-info/RECORD
