Metadata-Version: 2.1
Name: brownie-safe
Version: 0.9.2
Summary: Build complex Gnosis Safe transactions and safely preview them in a forked environment.
Home-page: https://github.com/banteg/brownie-safe
License: MIT
Author: banteg
Requires-Python: >=3.10,<3.13
Classifier: License :: OSI Approved :: MIT License
Classifier: Programming Language :: Python :: 3
Classifier: Programming Language :: Python :: 3.10
Classifier: Programming Language :: Python :: 3.11
Classifier: Programming Language :: Python :: 3.12
Requires-Dist: eth-brownie (>=1.20.7)
Requires-Dist: safe-eth-py (>=6.0.0,<7)
Requires-Dist: trezor (>=0.13.8)
Project-URL: Repository, https://github.com/banteg/brownie-safe
